csr/__init__.py
csr/_rows.py
csr/_struct.py
csr/_util.py
csr/_wiring.py
csr/constructors.py
csr/csr.py
csr/kernel.py
csr/structure.py
csr/test_utils.py
csr/transform.py
csr/kernels/__init__.py
csr/kernels/scipy.py
csr/kernels/mkl/__init__.py
csr/kernels/mkl/_api.py
csr/kernels/mkl/handle.py
csr/kernels/mkl/mkl_ops.c
csr/kernels/mkl/mkl_ops.h
csr/kernels/mkl/multiply.py
csr/kernels/numba/__init__.py
csr/kernels/numba/multiply.py
csr-0.5.2.dist-info/LICENSE
csr-0.5.2.dist-info/WHEEL
csr-0.5.2.dist-info/METADATA
csr-0.5.2.dist-info/RECORD
