Metadata-Version: 2.1
Name: csr
Version: 0.5.2
Summary: Compressed Sparse Row matrices for Python, with Numba API.
Author-email: Michael Ekstrand <michaelekstrand@boisestate.edu>
Requires-Python: >= 3.8
Classifier: License :: OSI Approved :: MIT License
Classifier: Intended Audience :: Science/Research
Requires-Dist: numba >=0.51
Requires-Dist: numpy >=1.21
Requires-Dist: scipy >=1.4,<2
Requires-Dist: flit >=3.2,<4 ; extra == "dev"
Requires-Dist: packaging ; extra == "dev"
Requires-Dist: tomlkit ; extra == "dev"
Requires-Dist: keyring ; extra == "dev"
Requires-Dist: docopt>=0.6 ; extra == "dev"
Requires-Dist: invoke ; extra == "dev"
Requires-Dist: flake8 ; extra == "dev"
Requires-Dist: rstcheck ; extra == "dev"
Requires-Dist: sphinx-autobuild >=2021 ; extra == "dev"
Requires-Dist: sphinx >=4 ; extra == "doc"
Requires-Dist: furo ; extra == "doc"
Requires-Dist: cffi ; extra == "mkl"
Requires-Dist: notebook ; extra == "profile"
Requires-Dist: seaborn ; extra == "profile"
Requires-Dist: jupytext ; extra == "profile"
Requires-Dist: pandas >=1.0 ; extra == "profile"
Requires-Dist: pytest ==7.* ; extra == "test"
Requires-Dist: pytest-doctestplus >=0.9 ; extra == "test"
Requires-Dist: pytest-benchmark >=3 ; extra == "test"
Requires-Dist: pytest-cov >=2.12 ; extra == "test"
Requires-Dist: hypothesis >=6.30,<7 ; extra == "test"
Requires-Dist: psutil >=5 ; extra == "test"
Project-URL: home-page, https://csr.lenskit.org
Project-URL: source, https://github.com/lenskit/csr
Provides-Extra: dev
Provides-Extra: doc
Provides-Extra: mkl
Provides-Extra: profile
Provides-Extra: test
